[  
   {  
      "id":40,
      "titleKo":"1.4.0 업데이트",
      "titleEn":"Update Notice",
      "titleImage":"https://eosknights.io/img/notice/newitem.png",
      "bodyKo":"![](https://eosknights.io/img/notice/notice1.png =256x256)\n\n## 1.4.0 업데이트\n* 신규장비 10종 추가\n* 추가 월렛 지원 (안드로이드)\n\n## 안드로이드 월렛 서포트\nNova월렛과 Math월렛이 안드로이드에서 지원됩니다. 해당 지갑앱을 최신버전으로 업데이트 해주세요.\n![](https://eosknights.io/img/notice/novamath.png =334x170)\n\n* [Nova 월렛 다운로드](https://play.google.com/store/apps/details?id=io.eosnova.wallet.android)\n* [Math 월렛 다운로드](http://www.mathwallet.org/en/)\n\n## 신규 장비 업데이트\n### 왕의 세트\n![](https://eosknights.io/img/notice/kingset.png =516x113)\n\n### 도리아 세트\n![](https://eosknights.io/img/notice/doricset.png =410x107)\n\n### 콜오브 밋원\n![](https://eosknights.io/img/resource/origin/item/item_825.png =100x100)\n\n## 보스던전 업데이트 안내\n보스던전은 유저분들께 새로운 전투의 재미를 드리기 위해 자동 전투 + 수동 스킬방식에서, 하스스톤 스타일의 턴 방식으로 재개발 되고 있습니다. 현재 40% 정도가 개발되었고 3주정도의 시간이 더 필요할 것 같습니다. 전투 스타일을 바꾸다 보니 일정이 미뤄지고 있습니다. 약속드린 일정을 지키지 못해 죄송합니다. 진행중인 작업을 미리 조금 공개드립니다.\n\n### AS-IS\n자동 전투 + 수동 스킬방식\n![](https://eosknights.io/img/notice/boss_old.jpg =400x218)\n\n### TO-BE\n하스스톤 스타일의 턴 방식\n![](https://eosknights.io/img/notice/boss2.jpg =400x711)\n\n보스전에 대한 좀더 자세한 정보는 아래 아래 이미지를 참고하세요. 추가되는 재료와 장비, 던전 몹, 스테이지를 일부 확인할수 있습니다.\n* [보스전 업데이트 예고](http://eosknights.io/img/dungeon.png)\n\n기대하시는 보스전이 늦어지고 있는점 죄송합니다. 열심히 준비해서 좋은 컨텐츠로 12월 12일날 찾아뵐수 있도록 노력하겠습니다. 감사합니다.",
      "bodyEn":"![](https://eosknights.io/img/notice/notice1.png =256x256)\n\n## 1.4.0 업데이트\n* 신규장비 10종 추가\n* 추가 월렛 지원 (안드로이드)\n\n## 안드로이드 월렛 서포트\nNova월렛과 Math월렛이 안드로이드에서 지원됩니다. 해당 지갑앱을 최신버전으로 업데이트 해주세요.\n![](https://eosknights.io/img/notice/novamath.png =334x170)\n\n* [Nova 월렛 다운로드](https://play.google.com/store/apps/details?id=io.eosnova.wallet.android)\n* [Math 월렛 다운로드](http://www.mathwallet.org/en/)\n\n## 신규 장비 업데이트\n### 왕의 세트\n![](https://eosknights.io/img/notice/kingset.png =516x113)\n\n### 도리아 세트\n![](https://eosknights.io/img/notice/doricset.png =410x107)\n\n### 콜오브 밋원\n![](https://eosknights.io/img/resource/origin/item/item_825.png =100x100)\n\n## 보스던전 업데이트 안내\n보스던전은 유저분들께 새로운 전투의 재미를 드리기 위해 자동 전투 + 수동 스킬방식에서, 하스스톤 스타일의 턴 방식으로 재개발 되고 있습니다. 현재 40% 정도가 개발되었고 3주정도의 시간이 더 필요할 것 같습니다. 전투 스타일을 바꾸다 보니 일정이 미뤄지고 있습니다. 약속드린 일정을 지키지 못해 죄송합니다. 진행중인 작업을 미리 조금 공개드립니다.\n\n### AS-IS\n자동 전투 + 수동 스킬방식\n![](https://eosknights.io/img/notice/boss_old.jpg =400x218)\n\n### TO-BE\n하스스톤 스타일의 턴 방식\n![](https://eosknights.io/img/notice/boss2.jpg =400x711)\n\n보스전에 대한 좀더 자세한 정보는 아래 아래 이미지를 참고하세요. 추가되는 재료와 장비, 던전 몹, 스테이지를 일부 확인할수 있습니다.\n* [보스전 업데이트 예고](http://eosknights.io/img/dungeon.png)\n\n기대하시는 보스전이 늦어지고 있는점 죄송합니다. 열심히 준비해서 좋은 컨텐츠로 12월 12일날 찾아뵐수 있도록 노력하겠습니다. 감사합니다.",
      "datetime":"2018-11-21T00:00:00.000",
      "expiration":"2018-11-25T00:00:00.000",
      "padding":40,
      "needPopup":true,
      "link":""
   }
]